kvhot/__main__.py
kvhot-2024.9.12.dist-info/LICENSE
kvhot-2024.9.12.dist-info/METADATA
kvhot-2024.9.12.dist-info/WHEEL
kvhot-2024.9.12.dist-info/entry_points.txt
kvhot-2024.9.12.dist-info/top_level.txt
kvhot-2024.9.12.dist-info/RECORD
