Metadata-Version: 2.1
Name: kvhot
Version: 2024.9.12
Summary: Automatically restarts the Kivy application whenever files within the project directory change.
Author-email: "Kulothungan U.G" <kulothunganug@gmail.com>, Alexander Hellier <alex.hellier@gmail.com>
License: MIT License
Project-URL: Homepage, https://github.com/kulothunganug/kvhot
Project-URL: Issues, https://github.com/kulothunganug/issues
Keywords: kivy,kivymd,hotrestart,gui
Classifier: Environment :: Console
Classifier: Programming Language :: Python
Classifier: Programming Language :: Python :: 3
Classifier: Programming Language :: Python :: 3 :: Only
Classifier: Programming Language :: Python :: 3.8
Classifier: Programming Language :: Python :: 3.9
Classifier: Programming Language :: Python :: 3.10
Classifier: Programming Language :: Python :: 3.11
Classifier: Programming Language :: Python :: 3.12
Classifier: Intended Audience :: Developers
Classifier: Intended Audience :: Information Technology
Classifier: License :: OSI Approved :: MIT License
Classifier: Operating System :: POSIX :: Linux
Classifier: Operating System :: Microsoft :: Windows
Classifier: Operating System :: MacOS
Classifier: Topic :: Software Development :: Libraries :: Python Modules
Classifier: Topic :: Software Development :: User Interfaces
Requires-Python: >=3.8
License-File: LICENSE
Requires-Dist: watchfiles>=0.18.1
Provides-Extra: dev
Requires-Dist: black; extra == "dev"
Requires-Dist: isort; extra == "dev"
Requires-Dist: flake8; extra == "dev"
Requires-Dist: pip-tools; extra == "dev"
